[{"model": "community.article", "pk": 3, "fields": {"user": 1, "game": 1085660, "title": "[인생게임] Destiny 2", "content": "데스티니 가디언즈는 총 쏘는 맛 하나만큼은 진짜 독보적인 게임이에요.\n압도적인 SF 배경과 화려한 연출 덕분에 눈이 즐겁죠.\n다만 뉴비가 적응하기에 좀 불친절하고 노가다가 심한 편이지만, 슈팅 게임을 좋아한다면 꼭 한 번쯤 해볼 만한 마성의 게임입니다.", "created_at": "2025-12-25T07:16:08.295Z", "updated_at": "2025-12-25T16:14:22.485Z"}}, {"model": "community.article", "pk": 4, "fields": {"user": 1, "game": 271590, "title": "[인생게임] Grand Theft Auto V Legacy", "content": "갓겜 그타 다들 같이해", "created_at": "2025-12-25T14:44:18.472Z", "updated_at": "2025-12-25T16:08:35.182Z"}}, {"model": "community.review", "pk": 3, "fields": {"user": 1, "game": 1174180, "rating_fun": 3, "rating_story": 2, "rating_control": 3, "rating_sound": 4, "rating_optimization": 3, "content": "서부 시대의 끝자락을 완벽하게 구현한 걸작입니다.\n아서 모건의 깊은 서사와 압도적인 디테일은 경이로운 몰입감을 선사하죠.\n조작감은 다소 묵직하지만, 그만큼 깊은 여운을 남기는 '인생 게임'으로 강력 추천합니다.", "created_at": "2025-12-25T05:34:06.856Z", "updated_at": "2025-12-25T16:13:23.737Z"}}, {"model": "community.review", "pk": 4, "fields": {"user": 1, "game": 892970, "rating_fun": 1, "rating_story": 1, "rating_control": 1, "rating_sound": 1, "rating_optimization": 3, "content": "마인크래프트가 더 재밌어요", "created_at": "2025-12-25T07:14:50.629Z", "updated_at": "2025-12-25T16:10:16.887Z"}}, {"model": "community.review", "pk": 5, "fields": {"user": 1, "game": 391540, "rating_fun": 4, "rating_story": 5, "rating_control": 3, "rating_sound": 5, "rating_optimization": 3, "content": "와 샌즈 겁나 재밌습니다", "created_at": "2025-12-25T07:18:48.135Z", "updated_at": "2025-12-25T16:11:04.828Z"}}, {"model": "community.review", "pk": 6, "fields": {"user": 1, "game": 477160, "rating_fun": 5, "rating_story": 4, "rating_control": 4, "rating_sound": 4, "rating_optimization": 3, "content": "흐물흐물해서 귀여워요", "created_at": "2025-12-25T07:25:37.975Z", "updated_at": "2025-12-25T16:09:00.197Z"}}, {"model": "community.review", "pk": 7, "fields": {"user": 3, "game": 3101040, "rating_fun": 5, "rating_story": 5, "rating_control": 5, "rating_sound": 5, "rating_optimization": 5, "content": "갓겜으 ㄴ나다!!!!!!!", "created_at": "2025-12-25T08:12:21.799Z", "updated_at": "2025-12-25T08:12:21.799Z"}}, {"model": "community.review", "pk": 8, "fields": {"user": 3, "game": 2252960, "rating_fun": 5, "rating_story": 5, "rating_control": 5, "rating_sound": 5, "rating_optimization": 5, "content": "이게 모에요ㄹ호ㅠㅊ퐇츄푸", "created_at": "2025-12-25T08:12:40.794Z", "updated_at": "2025-12-25T08:12:40.794Z"}}, {"model": "community.review", "pk": 9, "fields": {"user": 1, "game": 271590, "rating_fun": 5, "rating_story": 3, "rating_control": 4, "rating_sound": 2, "rating_optimization": 2, "content": "별로 안해봤는데 재밌어요", "created_at": "2025-12-25T08:28:01.914Z", "updated_at": "2025-12-25T16:09:26.095Z"}}, {"model": "community.review", "pk": 10, "fields": {"user": 4, "game": 1086940, "rating_fun": 5, "rating_story": 5, "rating_control": 4, "rating_sound": 4, "rating_optimization": 5, "content": "갓겜 인정합니다!!!!", "created_at": "2025-12-25T09:26:28.484Z", "updated_at": "2025-12-25T09:26:28.484Z"}}]